{
  "schemaVersion": 2,
  "metroId": "honolulu",
  "generatedAt": "2026-06-02T03:33:32.603Z",
  "source": {
    "name": "Honolulu event source registry",
    "registryPath": "data/event-sources-honolulu.json",
    "sourceCount": 12,
    "attribution": "Official source pages and configured public event feeds"
  },
  "coverage": {
    "cities": [
      "Honolulu",
      "Waikiki",
      "Pearl City",
      "Aiea",
      "Kailua",
      "Kaneohe",
      "Kapolei",
      "Ewa Beach",
      "Mililani",
      "Haleiwa",
      "Waipahu",
      "Pāhoa",
      "Hilo",
      "Lihue",
      "Wailuku",
      "Lahaina",
      "Kihei",
      "Kahului",
      "Laupāhoehoe",
      "Chinatown",
      "Kakaako"
    ]
  },
  "count": 9,
  "events": [
    {
      "id": "hawaii-state-library-lego-day-edf03d08e0",
      "baseId": null,
      "title": "LEGO Day!",
      "description": "LEGO Day! June 2, 2026 O‘ahu - Waikīkī-Kapahulu 400 Kapahulu Ave, Honolulu, HI, United States We love LEGO! Join us and build something for us to display around the library. LEGOs will be out all day long for our building [&hellip;]",
      "venue": "Hawaii State Public Library System",
      "city": "Honolulu",
      "neighborhood": "Honolulu",
      "lat": 21.3069,
      "lon": -157.8583,
      "category": "Library",
      "daysOfWeek": [
        1
      ],
      "timeWindow": "Evening",
      "startDateTime": "2026-06-02T00:00:00.000Z",
      "endDateTime": "2026-06-02T01:00:00.000Z",
      "ageBands": [
        "school-age"
      ],
      "audiences": [
        "all"
      ],
      "cost": "Unknown",
      "url": "https://www.librarieshawaii.org/event/lego-day-2026-06-02/",
      "sourceUrl": "https://www.librarieshawaii.org/events",
      "sourceId": "hawaii-state-library",
      "sourceName": "Hawaii State Public Library System",
      "sourceMode": "html",
      "extractionMethod": "html",
      "verified": false,
      "fetchedAt": "2026-06-02T03:33:32.603Z",
      "metroId": "honolulu",
      "themes": [
        "stem"
      ],
      "slug": "lego-day-hawaii-state-public-library-system"
    },
    {
      "id": "hawaii-state-library-mahjong-at-the-library-1001aaa36b",
      "baseId": null,
      "title": "Mahjong At The Library",
      "description": "Interested in playing basic mahjong? Stop by the Ewa Beach Public & School Library for a chance to learn and play! Anyone who requires an [&hellip;] \\n",
      "venue": "O‘ahu – ʻEwa Beach",
      "city": "ʻEwa Beach",
      "neighborhood": "ʻEwa Beach",
      "lat": 21.3133874,
      "lon": -158.0091839,
      "category": "Library",
      "daysOfWeek": [
        1
      ],
      "timeWindow": "Evening",
      "startDateTime": "2026-06-02T01:00:00.000Z",
      "endDateTime": "2026-06-02T03:00:00.000Z",
      "ageBands": [
        "preschool",
        "school-age"
      ],
      "audiences": [
        "all"
      ],
      "cost": "Unknown",
      "url": "https://www.librarieshawaii.org/event/mahjong/2026-06-01/",
      "sourceUrl": "https://www.librarieshawaii.org/events",
      "sourceId": "hawaii-state-library",
      "sourceName": "Hawaii State Public Library System",
      "sourceMode": "json-ld",
      "extractionMethod": "json-ld",
      "verified": true,
      "fetchedAt": "2026-06-02T03:33:32.603Z",
      "metroId": "honolulu",
      "themes": [],
      "slug": "mahjong-at-the-library-o-ahu-ewa-beach"
    },
    {
      "id": "hawaii-state-library-kaua-i-live-poets-society-monthly-workshop-51ef065226",
      "baseId": null,
      "title": "Kaua’i Live Poets Society Monthly Workshop",
      "description": "Join the Kaua‘i Live Poets Society for a relaxed poetry workshop at the Līhu‘e Public Library. Open to new, adult members of all skill levels! [&hellip;] \\n",
      "venue": "Kaua‘i – Līhuʻe",
      "city": "Līhuʻe",
      "neighborhood": "Līhuʻe",
      "lat": 21.9768852,
      "lon": -159.3646977,
      "category": "Library",
      "daysOfWeek": [
        1
      ],
      "timeWindow": "Evening",
      "startDateTime": "2026-06-02T02:30:00.000Z",
      "endDateTime": "2026-06-02T04:00:00.000Z",
      "ageBands": [
        "preschool",
        "school-age"
      ],
      "audiences": [
        "all"
      ],
      "cost": "Unknown",
      "url": "https://www.librarieshawaii.org/event/kauai-live-poets-society-monthly-workshop-3/",
      "sourceUrl": "https://www.librarieshawaii.org/events",
      "sourceId": "hawaii-state-library",
      "sourceName": "Hawaii State Public Library System",
      "sourceMode": "json-ld",
      "extractionMethod": "json-ld",
      "verified": true,
      "fetchedAt": "2026-06-02T03:33:32.603Z",
      "metroId": "honolulu",
      "themes": [],
      "slug": "kaua-i-live-poets-society-monthly-workshop-kaua-i-lihue"
    },
    {
      "id": "hawaii-state-library-chess-club-d171b76587",
      "baseId": null,
      "title": "Chess Club",
      "description": "Strategy! Mental exercise! Chess Club! Join us and learn to play or brush up on your skills. Both beginners and veteran players are welcome to [&hellip;] \\n",
      "venue": "Hawai‘i – North Kohala",
      "city": "Kapa'au",
      "neighborhood": "Kapa'au",
      "lat": 20.2377874,
      "lon": -155.8148609,
      "category": "Library",
      "daysOfWeek": [
        1
      ],
      "timeWindow": "Evening",
      "startDateTime": "2026-06-02T03:00:00.000Z",
      "endDateTime": "2026-06-02T05:00:00.000Z",
      "ageBands": [
        "preschool",
        "school-age"
      ],
      "audiences": [
        "all"
      ],
      "cost": "Unknown",
      "url": "https://www.librarieshawaii.org/event/chess-club-north-kohala-6-01-26/",
      "sourceUrl": "https://www.librarieshawaii.org/events",
      "sourceId": "hawaii-state-library",
      "sourceName": "Hawaii State Public Library System",
      "sourceMode": "json-ld",
      "extractionMethod": "json-ld",
      "verified": true,
      "fetchedAt": "2026-06-02T03:33:32.603Z",
      "metroId": "honolulu",
      "themes": [],
      "slug": "chess-club-hawai-i-north-kohala"
    },
    {
      "id": "hawaii-state-library-movie-night-napoleon-dynamite-4e622fc0e7",
      "baseId": null,
      "title": "Movie Night – Napoleon Dynamite",
      "description": "It\\'s that time again! What time, you ask? Why, it\\'s the start of Summer At the Library! To kick off the summer, and start of [&hellip;] \\n",
      "venue": "Hawai‘i – Pāhoa",
      "city": "Pāhoa",
      "neighborhood": "Pāhoa",
      "lat": 19.4907595,
      "lon": -154.9411866,
      "category": "Library",
      "daysOfWeek": [
        1
      ],
      "timeWindow": "Evening",
      "startDateTime": "2026-06-02T03:00:00.000Z",
      "endDateTime": "2026-06-02T05:00:00.000Z",
      "ageBands": [
        "preschool",
        "school-age"
      ],
      "audiences": [
        "all"
      ],
      "cost": "Unknown",
      "url": "https://www.librarieshawaii.org/event/movie-night-napoleon-dynamite-2/",
      "sourceUrl": "https://www.librarieshawaii.org/events",
      "sourceId": "hawaii-state-library",
      "sourceName": "Hawaii State Public Library System",
      "sourceMode": "json-ld",
      "extractionMethod": "json-ld",
      "verified": true,
      "fetchedAt": "2026-06-02T03:33:32.603Z",
      "metroId": "honolulu",
      "themes": [],
      "slug": "movie-night-napoleon-dynamite-hawai-i-pahoa"
    },
    {
      "id": "hawaii-state-library-hui-lei-lei-making-club-71b51eb9f0",
      "baseId": null,
      "title": "Hui Lei – Lei Making Club",
      "description": "Join us for Nānākuli Public Library’s Hui Lei, a lei making club where you can create lei, talk story, and learn together. This program is [&hellip;] \\n",
      "venue": "O‘ahu – Nānākuli",
      "city": "Waianae",
      "neighborhood": "Waianae",
      "lat": 21.3821564,
      "lon": -158.1452652,
      "category": "Library",
      "daysOfWeek": [
        1
      ],
      "timeWindow": "Evening",
      "startDateTime": "2026-06-02T03:30:00.000Z",
      "endDateTime": "2026-06-30T05:00:00.000Z",
      "ageBands": [
        "preschool",
        "school-age"
      ],
      "audiences": [
        "all"
      ],
      "cost": "Unknown",
      "url": "https://www.librarieshawaii.org/event/hui-lei-lei-making-club-2-3-2-2/2026-06-01/",
      "sourceUrl": "https://www.librarieshawaii.org/events",
      "sourceId": "hawaii-state-library",
      "sourceName": "Hawaii State Public Library System",
      "sourceMode": "json-ld",
      "extractionMethod": "json-ld",
      "verified": true,
      "fetchedAt": "2026-06-02T03:33:32.603Z",
      "metroId": "honolulu",
      "themes": [
        "story-time"
      ],
      "slug": "hui-lei-lei-making-club-o-ahu-nanakuli"
    },
    {
      "id": "hawaii-state-library-a-taste-of-the-community-weekly-raffle-afadc08e78",
      "baseId": null,
      "title": "A Taste of the Community Weekly Raffle",
      "description": "Summer Reading Challenge participants have a chance to win a gift card from a local food spot! Sign up for Summer Reading and visit each [&hellip;] \\n",
      "venue": "Hawai‘i – Kailua-Kona",
      "city": "Kailua-Kona",
      "neighborhood": "Kailua-Kona",
      "lat": 19.6378443,
      "lon": -155.991081,
      "category": "Library",
      "daysOfWeek": [
        2
      ],
      "timeWindow": "Morning",
      "startDateTime": "2026-06-02T10:00:00.000Z",
      "endDateTime": "2026-06-03T09:59:59.000Z",
      "ageBands": [
        "preschool",
        "school-age"
      ],
      "audiences": [
        "all"
      ],
      "cost": "Unknown",
      "url": "https://www.librarieshawaii.org/event/a-taste-of-the-community-weekly-raffle/2026-06-02/",
      "sourceUrl": "https://www.librarieshawaii.org/events",
      "sourceId": "hawaii-state-library",
      "sourceName": "Hawaii State Public Library System",
      "sourceMode": "json-ld",
      "extractionMethod": "json-ld",
      "verified": true,
      "fetchedAt": "2026-06-02T03:33:32.603Z",
      "metroId": "honolulu",
      "themes": [
        "story-time",
        "food-markets"
      ],
      "slug": "a-taste-of-the-community-weekly-raffle-hawai-i-kailua-kona"
    },
    {
      "id": "hawaii-state-library-lego-day-83c9d3c502",
      "baseId": null,
      "title": "LEGO Day!",
      "description": "We love LEGO! Join us and build something for us to display around the library. LEGOs will be out all day long for our building [&hellip;] \\n",
      "venue": "O‘ahu – Waikīkī-Kapahulu",
      "city": "Honolulu",
      "neighborhood": "Honolulu",
      "lat": 21.2736666,
      "lon": -157.8165071,
      "category": "Library",
      "daysOfWeek": [
        2
      ],
      "timeWindow": "Morning",
      "startDateTime": "2026-06-02T10:00:00.000Z",
      "endDateTime": "2026-06-03T09:59:59.000Z",
      "ageBands": [
        "school-age"
      ],
      "audiences": [
        "all"
      ],
      "cost": "Unknown",
      "url": "https://www.librarieshawaii.org/event/lego-day-2026-06-02/",
      "sourceUrl": "https://www.librarieshawaii.org/events",
      "sourceId": "hawaii-state-library",
      "sourceName": "Hawaii State Public Library System",
      "sourceMode": "json-ld",
      "extractionMethod": "json-ld",
      "verified": true,
      "fetchedAt": "2026-06-02T03:33:32.603Z",
      "metroId": "honolulu",
      "themes": [
        "stem"
      ],
      "slug": "lego-day-o-ahu-waikiki-kapahulu"
    },
    {
      "id": "hawaii-state-library-puzzle-and-play-day-08952ac775",
      "baseId": null,
      "title": "Puzzle and Play Day",
      "description": "Come enjoy games and puzzles at the library! A small selection of games and puzzles of different varieties and difficulties will be on hand. With [&hellip;] \\n",
      "venue": "O‘ahu – Kalihi-Pālama",
      "city": "Honolulu",
      "neighborhood": "Honolulu",
      "lat": 21.3333242,
      "lon": -157.8723748,
      "category": "Library",
      "daysOfWeek": [
        2
      ],
      "timeWindow": "Afternoon",
      "startDateTime": "2026-06-02T19:15:00.000Z",
      "endDateTime": "2026-06-02T20:30:00.000Z",
      "ageBands": [
        "preschool",
        "school-age"
      ],
      "audiences": [
        "all"
      ],
      "cost": "Unknown",
      "url": "https://www.librarieshawaii.org/event/puzzle-and-play-day-kalihi-2-2-2-2-2-2-3/",
      "sourceUrl": "https://www.librarieshawaii.org/events",
      "sourceId": "hawaii-state-library",
      "sourceName": "Hawaii State Public Library System",
      "sourceMode": "json-ld",
      "extractionMethod": "json-ld",
      "verified": true,
      "fetchedAt": "2026-06-02T03:33:32.603Z",
      "metroId": "honolulu",
      "themes": [],
      "slug": "puzzle-and-play-day-o-ahu-kalihi-palama"
    }
  ]
}
